llmada_cpp/__init__.py
llmada_cpp/core.py
llmada_cpp/log.py
llmada_cpp/server.py
llmada_cpp-0.1.1.dist-info/METADATA
llmada_cpp-0.1.1.dist-info/WHEEL
llmada_cpp-0.1.1.dist-info/top_level.txt
llmada_cpp-0.1.1.dist-info/RECORD
